terminal_server.py
iflow_mcp_theailanguage_terminal_server-0.1.0.dist-info/METADATA
iflow_mcp_theailanguage_terminal_server-0.1.0.dist-info/WHEEL
iflow_mcp_theailanguage_terminal_server-0.1.0.dist-info/entry_points.txt
iflow_mcp_theailanguage_terminal_server-0.1.0.dist-info/licenses/LICENSE.txt
iflow_mcp_theailanguage_terminal_server-0.1.0.dist-info/RECORD
