Metadata-Version: 2.4
Name: iflow-mcp_theailanguage-terminal_server
Version: 0.1.0
Summary: Add your description here
License-File: LICENSE.txt
Requires-Python: >=3.13
Requires-Dist: mcp[cli]>=1.3.0
